cpinow/__init__.py
cpinow/data/colombia.csv
cpinow/data/colombia.xlsx
cpinow/exc.py
cpinow/logger.py
cpinow/names.py
cpinow/retrievers/__init__.py
cpinow/retrievers/base.py
cpinow/retrievers/colombia.py
cpinow/schemas.py
cpinow/settings.py
cpinow-2025.7.8.dist-info/LICENSE
cpinow-2025.7.8.dist-info/METADATA
cpinow-2025.7.8.dist-info/WHEEL
cpinow-2025.7.8.dist-info/RECORD
